sheetcalc/__init__.py
sheetcalc/table.py
sheetcalc-0.1.8.dist-info/LICENSE
sheetcalc-0.1.8.dist-info/METADATA
sheetcalc-0.1.8.dist-info/WHEEL
sheetcalc-0.1.8.dist-info/top_level.txt
sheetcalc-0.1.8.dist-info/RECORD
