Metadata-Version: 2.1
Name: sheetcalc
Version: 0.1.8
Summary: extract insights from 2d tables
Home-page: https://github.com/satapathy/pypi-sheetcalc
Author: S Satapathy
Author-email: shubhakant.satapathy@gmail.com
License: UNKNOWN
Platform: UNKNOWN
Classifier: Programming Language :: Python :: 3
Classifier: License :: OSI Approved :: MIT License
Classifier: Operating System :: OS Independent
